airtest_helper/__init__.py
airtest_helper/core.py
airtest_helper/decorator.py
airtest_helper/dir.py
airtest_helper/lib.py
airtest_helper/log.py
airtest_helper/logwraper.py
airtest_helper/platform.py
airtest_helper/settings.py
airtest_helper/setup.py
airtest_helper/libs/__init__.py
airtest_helper/libs/android.py
airtest_helper/libs/extend.py
airtest_helper/libs/ios.py
airtest_helper/libs/poco.py
airtest_helper-0.1.1.dist-info/LICENSE
airtest_helper-0.1.1.dist-info/METADATA
airtest_helper-0.1.1.dist-info/WHEEL
airtest_helper-0.1.1.dist-info/top_level.txt
airtest_helper-0.1.1.dist-info/RECORD
