Metadata-Version: 2.1
Name: airtest-helper
Version: 0.1.1
Summary: This is my airtest helper package
Home-page: https://github.com/ckf10000/airtest-helper
Author: ckf10000
Author-email: ckf10000@sina.com
Classifier: Programming Language :: Python :: 3
Classifier: License :: OSI Approved :: MIT License
Classifier: Operating System :: OS Independent
License-File: LICENSE
Requires-Dist: packaging >=24.1
Requires-Dist: numpy ==1.26.4
Requires-Dist: airtest >=1.3.4
Requires-Dist: pocoui >=1.0.94
